{"cameraMode":{"drawMode":0,"name":"Shaded","section":"Shading Mode"},"sceneLighting":false,"audioPlay":false,"sceneViewState":{"m_AlwaysRefresh":true,"showFog":false,"showSkybox":false,"showFlares":true,"showImageEffects":true,"showParticleSystems":true,"showVisualEffectGraphs":true,"m_FxEnabled":false},"in2DMode":false,"pivot":{"x":-19.110000610351564,"y":-2.0349998474121095,"z":0.0},"rotation":{"x":-0.0670258179306984,"y":0.5839803814888,"z":-0.048470139503479007,"w":-0.8075456023216248},"size":0.8660253882408142,"orthographic":false}